{
  "updated": "2026-07-08T15:20:40.024914+00:00",
  "stocks": {
    "NVDA": {
      "price": 197.3,
      "previousClose": 195.89,
      "marketState": "REGULAR",
      "avg20d": 201.35,
      "forwardPE": 15.45
    },
    "MU": {
      "price": 923.59,
      "previousClose": 914.87,
      "marketState": "REGULAR",
      "avg20d": 1045.0,
      "forwardPE": 6.17
    },
    "VOO": {
      "price": 681.34,
      "previousClose": 685.83,
      "marketState": "REGULAR",
      "avg20d": 680.77
    },
    "QQQ": {
      "price": 703.47,
      "previousClose": 707.08,
      "marketState": "REGULAR",
      "avg20d": 719.49
    },
    "LITE": {
      "price": 698.0,
      "previousClose": 689.8,
      "marketState": "REGULAR",
      "avg20d": 832.46,
      "forwardPE": 38.5
    },
    "GOOGL": {
      "price": 362.01,
      "previousClose": 366.75,
      "marketState": "REGULAR",
      "avg20d": 358.12,
      "forwardPE": 24.87
    },
    "META": {
      "price": 603.17,
      "previousClose": 616.98,
      "marketState": "REGULAR",
      "avg20d": 577.25,
      "forwardPE": 16.38
    },
    "MSFT": {
      "price": 382.83,
      "previousClose": 388.05,
      "marketState": "REGULAR",
      "avg20d": 382.05,
      "forwardPE": 19.77
    },
    "VST": {
      "price": 153.38,
      "previousClose": 155.4,
      "marketState": "REGULAR",
      "avg20d": 156.38,
      "forwardPE": 14.19
    },
    "ETN": {
      "price": 392.64,
      "previousClose": 394.34,
      "marketState": "REGULAR",
      "avg20d": 406.18,
      "forwardPE": 24.89
    }
  }
}
